dynamodict/__init__.py
dynamodict/dynamodict.py
dynamodictionary-1.0.3.dist-info/METADATA
dynamodictionary-1.0.3.dist-info/WHEEL
dynamodictionary-1.0.3.dist-info/top_level.txt
dynamodictionary-1.0.3.dist-info/RECORD
